[
    {
        "id": 1388534400000,
        "author": "Pete Hunt",
        "text": "Hey there!"
    },
    {
        "id": 1420070400000,
        "author": "Paul O’Shannessy",
        "text": "React is super-super *great*!"
    },
    {
        "id": 1474198894829,
        "author": "asd",
        "text": "3sss"
    },
    {
        "id": 1474198902006,
        "author": "s",
        "text": "224ed"
    },
    {
        "id": 1474198905578,
        "author": "eee",
        "text": "2"
    },
    {
        "id": 1474205625302,
        "author": "Тфьь",
        "text": "фыв"
    },
    {
        "id": 1474205632169,
        "author": "ыыв",
        "text": "3ллфыв"
    },
    {
        "id": 1474205857465,
        "author": "asd",
        "text": "332"
    }
]